callhub/__init__.py
callhub/__version__.py
callhub/auth.py
callhub/bulk_upload_tools.py
callhub/callhub.py
callhub_python_wrapper-1.2.3.dist-info/LICENSE
callhub_python_wrapper-1.2.3.dist-info/METADATA
callhub_python_wrapper-1.2.3.dist-info/WHEEL
callhub_python_wrapper-1.2.3.dist-info/top_level.txt
callhub_python_wrapper-1.2.3.dist-info/RECORD
