Metadata-Version: 2.1
Name: callhub-python-wrapper
Version: 1.2.3
Summary: Python API Wrapper for the CallHub API
Home-page: https://github.com/jamesbrunet/callhub-python-wrapper
Author: James Brunet
Author-email: james@brunet.dev
License: The MIT License (MIT)
Keywords: callhub,api
Platform: UNKNOWN
Classifier: Development Status :: 2 - Pre-Alpha
Classifier: Environment :: Console
Classifier: Intended Audience :: Developers
Classifier: Programming Language :: Python
Classifier: Topic :: Software Development
Classifier: Programming Language :: Python :: 3.5
Classifier: Programming Language :: Python :: 3.6
Classifier: Programming Language :: Python :: 3.7
Classifier: Programming Language :: Python :: 3.8
Classifier: Programming Language :: Python :: Implementation :: CPython
Requires-Python: >=3.5
Requires-Dist: ratelimit (==2.2.1)
Requires-Dist: requests-futures (==1.0.0)
Requires-Dist: requests (==2.23.0)
